rev_auth/__init__.py
rev_auth/__main__.py
rev_auth/creds.py
rev_auth/token.py
rev_auth_helper-0.1.0.dist-info/licenses/LICENSE
rev_auth_helper-0.1.0.dist-info/METADATA
rev_auth_helper-0.1.0.dist-info/WHEEL
rev_auth_helper-0.1.0.dist-info/entry_points.txt
rev_auth_helper-0.1.0.dist-info/top_level.txt
rev_auth_helper-0.1.0.dist-info/RECORD
