Metadata-Version: 2.4
Name: rev-auth-helper
Version: 0.1.0
Summary: Shared helper to load Rev credentials and fetch access tokens
Author: Alex McIntosh
License: MIT
Project-URL: Homepage, https://github.com/agmcin/rev_auth_helper
Project-URL: Repository, https://github.com/agmcin/rev_auth_helper
Project-URL: Issues, https://github.com/agmcin/rev_auth_helper/issues
Keywords: rev,auth,vbrick,token
Classifier: Development Status :: 3 - Alpha
Classifier: Intended Audience :: Developers
Classifier: License :: OSI Approved :: MIT License
Classifier: Operating System :: OS Independent
Classifier: Programming Language :: Python
Classifier: Programming Language :: Python :: 3
Classifier: Programming Language :: Python :: 3 :: Only
Classifier: Programming Language :: Python :: 3.9
Classifier: Programming Language :: Python :: 3.10
Classifier: Programming Language :: Python :: 3.11
Classifier: Programming Language :: Python :: 3.12
Classifier: Topic :: Internet
Classifier: Topic :: Software Development :: Libraries
Classifier: Topic :: Utilities
Requires-Python: >=3.9
License-File: LICENSE
Requires-Dist: requests>=2.28
Dynamic: license-file
